bms_tree_modules/__init__.py
bms_tree_modules/config.py
bms_tree_modules/curves.py
bms_tree_modules/decision.py
bms_tree_modules/module.py
bms_tree_modules/node.py
bms_tree_modules/team.py
bms_tree_modules/tree.py
bms_tree_modules/utils/__init__.py
bms_tree_modules/utils/helper.py
bms_tree_modules-0.2.1.dist-info/METADATA
bms_tree_modules-0.2.1.dist-info/WHEEL
bms_tree_modules-0.2.1.dist-info/top_level.txt
bms_tree_modules-0.2.1.dist-info/RECORD
