Metadata-Version: 2.1
Name: bms-tree-modules
Version: 0.2.1
Summary: The package contains the generic building blocks for the period-based Banking Management Simulation Games developed by the Institue of Banking & Finance (University of Zurich, Switerland).
Home-page: https://gitlab.uzh.ch/uzh-bf/sim/banking-game-2020
Author: Moritz Eck
Author-email: moritz.eck@gmail.com
License: MIT
Project-URL: Documentation, https://gitlab.uzh.ch/uzh-bf/sim/banking-game-2020
Project-URL: Source Code, https://gitlab.uzh.ch/uzh-bf/sim/banking-game-2020
Platform: UNKNOWN
Classifier: License :: OSI Approved :: MIT License
Classifier: Programming Language :: Python
Classifier: Programming Language :: Python :: 3.8
Requires-Python: >=3.8
Requires-Dist: typing
Provides-Extra: dev
Requires-Dist: pylama ; extra == 'dev'
Requires-Dist: black ; extra == 'dev'
Requires-Dist: flake8 ; extra == 'dev'
Provides-Extra: tests
Requires-Dist: pytest ; extra == 'tests'
Requires-Dist: pytest-watch ; extra == 'tests'
